{"AAK": {"Kodu": "AAK", "TEFAS \u0130\u015flem Ba\u015flang\u0131\u00e7 Saati": "09:00", "Fon Al\u0131\u015f Val\u00f6r\u00fc": "1", "TEFAS Min. Al\u0131\u015f \u0130\u015flem Miktar\u0131 ": "1", "TEFAS Max. Al\u0131\u015f \u0130\u015flem Miktar\u0131 ": "\u00a0", "TEFAS \u0130\u015flem Durumu": "\u0130\u015flem G\u00f6r\u00fcyor", "\u00c7\u0131k\u0131\u015f Komisyonu": "\u00a0", "ISIN Kodu": "TRMAF1WWWWW4", "TEFAS Son \u0130\u015flem Saati": "17:30", "Fon Sat\u0131\u015f Val\u00f6r\u00fc": "1", "TEFAS Min. Sat\u0131\u015f \u0130\u015flem Miktar\u0131 ": "1", "TEFAS Max. Sat\u0131\u015f \u0130\u015flem Miktar\u0131 ": "\u00a0", "Giri\u015f Komisyonu": "\u00a0"}, "AAL": {"Kodu": "AAL", "TEFAS \u0130\u015flem Ba\u015flang\u0131\u00e7 Saati": "09:00", "Fon Al\u0131\u015f Val\u00f6r\u00fc": "0", "TEFAS Min. Al\u0131\u015f \u0130\u015flem Miktar\u0131 ": "10.000", "TEFAS Max. Al\u0131\u015f \u0130\u015flem Miktar\u0131 ": "\u00a0", "TEFAS \u0130\u015flem Durumu": "\u0130\u015flem G\u00f6r\u00fcyor", "\u00c7\u0131k\u0131\u015f Komisyonu": "\u00a0", "ISIN Kodu": "TRMAALWWWWW5", "TEFAS Son \u0130\u015flem Saati": "13:30", "Fon Sat\u0131\u015f Val\u00f6r\u00fc": "0", "TEFAS Min. Sat\u0131\u015f \u0130\u015flem Miktar\u0131 ": "10", "TEFAS Max. Sat\u0131\u015f \u0130\u015flem Miktar\u0131 ": "\u00a0", "Giri\u015f Komisyonu": "\u00a0"}, "AAS": {"Kodu": "AAS", "TEFAS \u0130\u015flem Ba\u015flang\u0131\u00e7 Saati": "09:00", "Fon Al\u0131\u015f Val\u00f6r\u00fc": "1", "TEFAS Min. Al\u0131\u015f \u0130\u015flem Miktar\u0131 ": "1", "TEFAS Max. Al\u0131\u015f \u0130\u015flem Miktar\u0131 ": "\u00a0", "TEFAS \u0130\u015flem Durumu": "\u0130\u015flem G\u00f6r\u00fcyor", "\u00c7\u0131k\u0131\u015f Komisyonu": "\u00a0", "ISIN Kodu": "TRYATAM00028", "TEFAS Son \u0130\u015flem Saati": "17:30", "Fon Sat\u0131\u015f Val\u00f6r\u00fc": "2", "TEFAS Min. Sat\u0131\u015f \u0130\u015flem Miktar\u0131 ": "1", "TEFAS Max. Sat\u0131\u015f \u0130\u015flem Miktar\u0131 ": "\u00a0", "Giri\u015f Komisyonu": "\u00a0"}, "AAV": {"Kodu": "AAV", "TEFAS \u0130\u015flem Ba\u015flang\u0131\u00e7 Saati": "09:00", "Fon Al\u0131\u015f Val\u00f6r\u00fc": "1", "TEFAS Min. Al\u0131\u015f \u0130\u015flem Miktar\u0131 ": "1", "TEFAS Max. Al\u0131\u015f \u0130\u015flem Miktar\u0131 ": "\u00a0", "TEFAS \u0130\u015flem Durumu": "\u0130\u015flem G\u00f6r\u00fcyor", "\u00c7\u0131k\u0131\u015f Komisyonu": "\u00a0", "ISIN Kodu": "TRYATAM00069", "TEFAS Son \u0130\u015flem Saati": "17:30", "Fon Sat\u0131\u015f Val\u00f6r\u00fc": "2", "TEFAS Min. Sat\u0131\u015f \u0130\u015flem Miktar\u0131 ": "1", "TEFAS Max. Sat\u0131\u015f \u0130\u015flem Miktar\u0131 ": "\u00a0", "Giri\u015f Komisyonu": "\u00a0"}, "ABU": {"Kodu": "ABU", "TEFAS \u0130\u015flem Ba\u015flang\u0131\u00e7 Saati": "\u00a0", "Fon Al\u0131\u015f Val\u00f6r\u00fc": "\u00a0", "TEFAS Min. Al\u0131\u015f \u0130\u015flem Miktar\u0131 ": "\u00a0", "TEFAS Max. Al\u0131\u015f \u0130\u015flem Miktar\u0131 ": "\u00a0", "TEFAS \u0130\u015flem Durumu": "\u0130\u015flem G\u00f6rm\u00fcyor", "\u00c7\u0131k\u0131\u015f Komisyonu": "\u00a0", "ISIN Kodu": "TRYAKBK00813", "TEFAS Son \u0130\u015flem Saati": "\u00a0", "Fon Sat\u0131\u015f Val\u00f6r\u00fc": "\u00a0", "TEFAS Min. Sat\u0131\u015f \u0130\u015flem Miktar\u0131 ": "\u00a0", "TEFAS Max. Sat\u0131\u015f \u0130\u015flem Miktar\u0131 ": "\u00a0", "Giri\u015f Komisyonu": "\u00a0"}}